core/__init__.py
core/analyseur.py
core/simulateur.py
exceptions/__init__.py
exceptions/analyseur_exceptions.py
exceptions/base_exceptions.py
exceptions/route_exceptions.py
exceptions/simulateur_exceptions.py
exceptions/vehicule_exceptions.py
io_pkg/__init__.py
io_pkg/affichage.py
io_pkg/export.py
models/__init__.py
models/reseau.py
models/route.py
models/vehicule.py
simulateur_trafic/__init__.py
simulateur_trafic/__main__.py
simulateur_trafic/main.py
simulateur_trafic/core/__init__.py
simulateur_trafic/core/analyseur.py
simulateur_trafic/core/simulateur.py
simulateur_trafic/data/config_reseau.json
simulateur_trafic/data/positions.csv
simulateur_trafic/data/resultats.json
simulateur_trafic/exceptions/__init__.py
simulateur_trafic/exceptions/analyseur_exceptions.py
simulateur_trafic/exceptions/base_exceptions.py
simulateur_trafic/exceptions/route_exceptions.py
simulateur_trafic/exceptions/simulateur_exceptions.py
simulateur_trafic/exceptions/vehicule_exceptions.py
simulateur_trafic/io_pkg/__init__.py
simulateur_trafic/io_pkg/affichage.py
simulateur_trafic/io_pkg/export.py
simulateur_trafic/models/__init__.py
simulateur_trafic/models/reseau.py
simulateur_trafic/models/route.py
simulateur_trafic/models/vehicule.py
simulateur_trafic_moatez-1.0.0.dist-info/licenses/LICENSE
simulateur_trafic_moatez-1.0.0.dist-info/METADATA
simulateur_trafic_moatez-1.0.0.dist-info/WHEEL
simulateur_trafic_moatez-1.0.0.dist-info/entry_points.txt
simulateur_trafic_moatez-1.0.0.dist-info/top_level.txt
simulateur_trafic_moatez-1.0.0.dist-info/RECORD
